raiden/__init__.py
raiden/__main__.py
raiden/_monkey.py
raiden/accounts.py
raiden/constants.py
raiden/exceptions.py
raiden/log_config.py
raiden/message_handler.py
raiden/py.typed
raiden/raiden_event_handler.py
raiden/raiden_service.py
raiden/routing.py
raiden/services.py
raiden/settings.py
raiden/tasks.py
raiden/waiting.py
raiden/api/__init__.py
raiden/api/exceptions.py
raiden/api/objects.py
raiden/api/python.py
raiden/api/rest.py
raiden/api/rest_utils.py
raiden/api/v1/__init__.py
raiden/api/v1/encoding.py
raiden/api/v1/resources.py
raiden/blockchain/__init__.py
raiden/blockchain/decode.py
raiden/blockchain/events.py
raiden/blockchain/exceptions.py
raiden/blockchain/filters.py
raiden/blockchain/state.py
raiden/blockchain/utils.py
raiden/messages/__init__.py
raiden/messages/abstract.py
raiden/messages/cmdid.py
raiden/messages/decode.py
raiden/messages/encode.py
raiden/messages/healthcheck.py
raiden/messages/metadata.py
raiden/messages/monitoring_service.py
raiden/messages/path_finding_service.py
raiden/messages/synchronization.py
raiden/messages/transfers.py
raiden/messages/withdraw.py
raiden/network/__init__.py
raiden/network/pathfinding.py
raiden/network/utils.py
raiden/network/proxies/__init__.py
raiden/network/proxies/custom_token.py
raiden/network/proxies/exceptions.py
raiden/network/proxies/metadata.py
raiden/network/proxies/monitoring_service.py
raiden/network/proxies/one_to_n.py
raiden/network/proxies/payment_channel.py
raiden/network/proxies/proxy_manager.py
raiden/network/proxies/secret_registry.py
raiden/network/proxies/service_registry.py
raiden/network/proxies/token.py
raiden/network/proxies/token_network.py
raiden/network/proxies/token_network_registry.py
raiden/network/proxies/user_deposit.py
raiden/network/proxies/utils.py
raiden/network/resolver/__init__.py
raiden/network/resolver/client.py
raiden/network/rpc/__init__.py
raiden/network/rpc/client.py
raiden/network/rpc/middleware.py
raiden/network/transport/__init__.py
raiden-3.0.1.dist-info/LICENSE
raiden-3.0.1.dist-info/METADATA
raiden-3.0.1.dist-info/WHEEL
raiden-3.0.1.dist-info/entry_points.txt
raiden-3.0.1.dist-info/top_level.txt
raiden-3.0.1.dist-info/RECORD
